CHANGELOG.rst
LICENSE
MANIFEST.in
README.md
setup.cfg
setup.py
docs/Makefile
docs/changelog.rst
docs/conf.py
docs/cut_material.md
docs/design.md
docs/diff_formats.md
docs/index.rst
docs/installation.rst
docs/old_tree_diff_logic.md
docs/requirements.txt
docs/specs.md
docs/spelling_wordlist.txt
docs/use_cases.md
src/.DS_Store
src/treediffer/__init__.py
src/treediffer/__main__.py
src/treediffer/cli.py
src/treediffer/diffutils.py
src/treediffer/presets.py
src/treediffer/treediffs.py
src/treediffer.egg-info/PKG-INFO
src/treediffer.egg-info/SOURCES.txt
src/treediffer.egg-info/dependency_links.txt
src/treediffer.egg-info/entry_points.txt
src/treediffer.egg-info/not-zip-safe
src/treediffer.egg-info/top_level.txt